autocar/__init__.py
autocar-0.1.18.dist-info/LICENSE
autocar-0.1.18.dist-info/WHEEL
autocar-0.1.18.dist-info/METADATA
autocar-0.1.18.dist-info/RECORD
