Metadata-Version: 2.1
Name: autocar
Version: 0.1.18
Summary: autocar
Author-email: Jean Henstock <63672596+jjhenstock@users.noreply.github.com>
Classifier: License :: OSI Approved :: MIT License
Requires-Dist: extract-msg
Requires-Dist: keyboard
Requires-Dist: numpy
Requires-Dist: openpyxl
Requires-Dist: pandas
Requires-Dist: PyAutoGUI
Requires-Dist: PyPDF2
Requires-Dist: pyperclip
Requires-Dist: xlwings==0.30.6
Requires-Dist: pyarrow
Project-URL: Home, https://github.com/jjhenstock/autocar
